sksurgerytf/__init__.py
sksurgerytf/_version.py
sksurgerytf/models/__init__.py
sksurgerytf/models/fashion.py
sksurgerytf/models/rgb_unet.py
sksurgerytf/ui/__init__.py
sksurgerytf/ui/sksurgery_fashion_command_line.py
sksurgerytf/ui/sksurgery_rgbunet_command_line.py
sksurgerytf/ui/sksurgery_segstats_command_line.py
sksurgerytf/utils/__init__.py
sksurgerytf/utils/segmentation_statistics.py
scikit_surgerytf-0.1.1.dist-info/LICENSE
scikit_surgerytf-0.1.1.dist-info/METADATA
scikit_surgerytf-0.1.1.dist-info/WHEEL
scikit_surgerytf-0.1.1.dist-info/entry_points.txt
scikit_surgerytf-0.1.1.dist-info/top_level.txt
scikit_surgerytf-0.1.1.dist-info/RECORD
