Metadata-Version: 2.1
Name: scikit-surgerytf
Version: 0.1.1
Summary: scikit-surgerytf is a Python package for Tensor Flow examples and utilities
Home-page: https://weisslab.cs.ucl.ac.uk/WEISS/SoftwareRepositories/SNAPPY/scikit-surgerytf
Author: Matt Clarkson
Author-email: m.clarkson@ucl.ac.uk
License: Apache Software License 2.0
Keywords: medical imaging
Platform: UNKNOWN
Classifier: Development Status :: 3 - Alpha
Classifier: Intended Audience :: Developers
Classifier: Intended Audience :: Healthcare Industry
Classifier: Intended Audience :: Information Technology
Classifier: Intended Audience :: Science/Research
Classifier: License :: OSI Approved :: Apache Software License
Classifier: Programming Language :: Python
Classifier: Programming Language :: Python :: 2
Classifier: Programming Language :: Python :: 3
Classifier: Topic :: Scientific/Engineering :: Information Analysis
Classifier: Topic :: Scientific/Engineering :: Medical Science Apps.
Requires-Dist: pyyaml
Requires-Dist: h5py
Requires-Dist: ipykernel
Requires-Dist: nbsphinx
Requires-Dist: Pillow
Requires-Dist: scipy
Requires-Dist: opencv-contrib-python (==4.1.1.26)
Requires-Dist: tensorflow (==2.0.0)
Requires-Dist: tensorflow-datasets (==1.3.0)
Requires-Dist: matplotlib (==3.1.1)
